ecom_statics/__init__.py
ecom_statics/static/ecom_statics/css/adminlte.css
ecom_statics/static/ecom_statics/css/adminlte_variables.css
ecom_statics/static/ecom_statics/css/custom_adminlte.css
ecom_statics/static/ecom_statics/css/variables.css
ecom_statics/static/ecom_statics/css/login/login.css
ecom_statics/static/ecom_statics/images/favicons/ecom.ico
ecom_statics/static/ecom_statics/images/loaders/ecom.gif
ecom_statics/static/ecom_statics/images/logos/ecom-logo.svg
ecom_statics/static/ecom_statics/images/logos/ecom.png
ecom_statics/static/ecom_statics/images/logos/usuario.png
ecom_statics/static/ecom_statics/js/adminlte.js
ecom_statics/static/ecom_statics/modules/select2/css/custom_select2.css
ecom_statics/static/ecom_statics/modules/select2/js/initialize_select2.js
ecom_statics/static/ecom_statics/modules/sidebar/js/sidebar.js
ecom_statics/static/ecom_statics/vendors/select2/css/select2.min.css
ecom_statics/static/ecom_statics/vendors/select2/js/select2.min.js
ecom_statics/templates/ecom_statics/base/base.html
ecom_statics/templates/ecom_statics/base/footer.html
ecom_statics/templates/ecom_statics/base/header.html
ecom_statics/templates/ecom_statics/base/sidebar.html
ecom_statics/templates/ecom_statics/includes/breadcrumb.html
ecom_statics/templates/ecom_statics/includes/create_buttons.html
ecom_statics/templates/ecom_statics/includes/empty_list.html
ecom_statics/templates/ecom_statics/includes/error_alert.html
ecom_statics/templates/ecom_statics/includes/form_errors.html
ecom_statics/templates/ecom_statics/includes/forms.html
ecom_statics/templates/ecom_statics/includes/list_buttons.html
ecom_statics/templates/ecom_statics/includes/pagination.html
ecom_statics/templates/ecom_statics/usuarios/login.html
ecom_statics/templates/ecom_statics/usuarios/login_v2.html
ecom_statics-0.1.11.dist-info/METADATA
ecom_statics-0.1.11.dist-info/WHEEL
ecom_statics-0.1.11.dist-info/top_level.txt
ecom_statics-0.1.11.dist-info/RECORD
