Metadata-Version: 2.4
Name: ecom_statics
Version: 0.1.11
Summary: Ecom statics
Home-page: https://git.ecom.com.ar/ecom-data/ecom_statics
Author: Ecom
Author-email: equipo.ecomdata@gmail.com
Classifier: Programming Language :: Python :: 3
Classifier: License :: OSI Approved :: MIT License
Requires-Python: >=3.8
Dynamic: author
Dynamic: author-email
Dynamic: classifier
Dynamic: description
Dynamic: description-content-type
Dynamic: home-page
Dynamic: requires-python
Dynamic: summary
